[
  {
    "title": "Project 1",
    "date": "2025",
    "tags": ["Website", "Software"],
    "description": [
      "Description of project 1.",
      "Another line of description for project 1."
    ],
    "technologies": ["HTML", "CSS", "JavaScript"],
    "imageUrl": "assets/images/hobbies/jeux-video.avif",
    "link": "google.com"
  },
  {
    "title": "Project 2",
    "date": "2024",
    "tags": ["Website", "Software"],
    "description": [
      "Description of project 2.",
      "Another line of description for project 2."
    ],
    "technologies": ["React", "Node.js"],
    "imageUrl": "assets/images/hobbies/jeux-video.avif",
    "link": "google.com"
  }
]
